{"stats":{"minecraft:used":{"minecraft:zombie_spawn_egg":5,"examplemod:rainbow_carpet_block":109},"minecraft:picked_up":{"examplemod:rainbow_carpet_block":1},"minecraft:custom":{"minecraft:jump":20,"minecraft:time_since_rest":2924,"minecraft:crouch_one_cm":74,"minecraft:leave_game":1,"minecraft:play_time":2924,"minecraft:time_since_death":2924,"minecraft:walk_one_cm":12544,"minecraft:sneak_time":67,"minecraft:total_world_time":7593,"minecraft:drop":1,"minecraft:fly_one_cm":15766},"minecraft:dropped":{"examplemod:rainbow_carpet_block":1}},"DataVersion":3218}